flask_markdown/__init__.py
flask_markdown/markdown.py
Flask_MD-0.4.1.dist-info/LICENSE
Flask_MD-0.4.1.dist-info/METADATA
Flask_MD-0.4.1.dist-info/WHEEL
Flask_MD-0.4.1.dist-info/top_level.txt
Flask_MD-0.4.1.dist-info/RECORD
